{"Albert Einstein": "3/14/1879", "Neils Bohr": "10/7/1885", "Henry Ford": "7/30/1863", "Benjamin Franklin": "1/17/1706", "Johnny Cash": "2/26/1932", "Abraham Lincoln": "2/12/1809", "Michael Jordan": "2/17/1963", "Thomas Jefferson": "4/13/1743", "Dwayne Johnson": "5/2/1972", "Clint Eastwood": "5/31/1930", "Harry Truman": "5/8/1884", "Yogi Berra": "5/12/1925", "Morgan Freeman": "6/1/1937", "Elon Musk": "6/28/1971", "Derek Jeter": "6/26/1974", "Andy Griffith": "6/1/1926", "John Adams": "10/30/1735", "Keanu Reeves": "9/2/1964", "Jesse Owens": "9/12/1913", "Matt Damon": "10/8/1970", "Theodore Roosevelt": "10/27/1858", "Barack Obama": "8/4/1961", "Neil Armstrong": "8/5/1930", "Andy Warhol": "8/6/1928", "Alfred Hitchcock": "8/13/1899", "Mark Twain": "11/30/1835", "Aaron Rodgers": "12/2/1983", "Frank Sinatra": "12/12/1915", "Isaac Newton": "12/25/1642", "Steven Spielberg": "12/18/1946", "Woodrow Wilson": "12/28/1856", "Ada Lovelace": "12/10/1815", "Taylor Swift": "12/12/1989", "Louis Pasteur": "12/27/1822", "Joan Of Arc": "1/6/1412", "Marie Curie": "11/7/1867", "Marie Antoinette": "11/2/1755", "Emily Dickinson": "5/15/1830", "Michael Jackson": "5/8/1958"}